.gitignore
LICENSE
readme.md
setup.py
tests/__init__.py
tests/test_netlist.py
tests/test_primitives.py
tests/test_vlsirtools.py
vlsirtools/__init__.py
vlsirtools/primitives.py
vlsirtools/pytest.py
vlsirtools/spicetype.py
vlsirtools.egg-info/PKG-INFO
vlsirtools.egg-info/SOURCES.txt
vlsirtools.egg-info/dependency_links.txt
vlsirtools.egg-info/requires.txt
vlsirtools.egg-info/top_level.txt
vlsirtools/netlist/__init__.py
vlsirtools/netlist/base.py
vlsirtools/netlist/fmt.py
vlsirtools/netlist/main.py
vlsirtools/netlist/spectre.py
vlsirtools/netlist/spectre_spice_shared.py
vlsirtools/netlist/spice.py
vlsirtools/netlist/verilog.py
vlsirtools/spectre/__init__.py
vlsirtools/spice/__init__.py
vlsirtools/spice/base.py
vlsirtools/spice/ngspice.py
vlsirtools/spice/sim_data.py
vlsirtools/spice/spectre.py
vlsirtools/spice/spice.py
vlsirtools/spice/xyce.py
vlsirtools/xyce/__init__.py