Metadata-Version: 2.1
Name: vlsirtools
Version: 7.0.0
Summary: Tools for the Vlsir IC Design Schema
Home-page: https://github.com/Vlsir/Vlsir
Author: Dan Fritchman
Author-email: dan@fritch.mn
Requires-Python: >=3.7, <3.13
Provides-Extra: dev
License-File: LICENSE
